<DOMSymbolItem xmlns:xsi="http://www.w3.org/2001/XMLSchema-instance" xmlns="http://ns.adobe.com/xfl/2008/" name="boy right leg.psd" itemID="5ee0c5d9-00000346" symbolType="graphic" lastModified="1591789017">
  <timeline>
    <DOMTimeline name="boy right leg.psd">
      <layers>
        <DOMLayer name="Layer 0" color="#9933CC" current="true" isSelected="true" autoNamed="false">
          <frames>
            <DOMFrame index="0" keyMode="9728">
              <elements>
                <DOMBitmapInstance selected="true" libraryItemName="boy right leg.psd Assets/Layer 0">
                  <matrix>
                    <Matrix tx="71" ty="32"/>
                  </matrix>
                </DOMBitmapInstance>
              </elements>
            </DOMFrame>
          </frames>
        </DOMLayer>
        <DOMLayer name="Layer 1" color="#4FFF4F">
          <frames>
            <DOMFrame index="0" keyMode="9728">
              <elements/>
            </DOMFrame>
          </frames>
        </DOMLayer>
      </layers>
    </DOMTimeline>
  </timeline>
</DOMSymbolItem>